creme-0.6.1.dist-info/top_level.txt
creme-0.6.1.dist-info/RECORD
creme-0.6.1.dist-info/METADATA
creme-0.6.1.dist-info/LICENSE
creme-0.6.1.dist-info/WHEEL
creme/__version__.py
creme/dummy.py
creme/__init__.py
creme/conftest.py
creme/test_.py
creme/base/predictor.py
creme/base/wrapper.py
creme/base/clusterer.py
creme/base/classifier.py
creme/base/typing.py
creme/base/multi_output.py
creme/base/regressor.py
creme/base/transformer.py
creme/base/anomaly.py
creme/base/__init__.py
creme/base/estimator.py
creme/base/test_base.py
creme/base/ensemble.py
creme/feature_extraction/vectorize.py
creme/feature_extraction/agg.py
creme/feature_extraction/__init__.py
creme/anomaly/hst.py
creme/anomaly/__init__.py
creme/cluster/k_means.py
creme/cluster/__init__.py
creme/reco/biased_mf.py
creme/reco/baseline.py
creme/reco/funk_mf.py
creme/reco/normal.py
creme/reco/surprise.py
creme/reco/base.py
creme/reco/__init__.py
creme/preprocessing/test_scale.py
creme/preprocessing/one_hot.py
creme/preprocessing/poly.py
creme/preprocessing/kernel_approx.py
creme/preprocessing/scale.py
creme/preprocessing/__init__.py
creme/preprocessing/feature_hasher.py
creme/facto/ffm.py
creme/facto/hofm.py
creme/facto/fm.py
creme/facto/base.py
creme/facto/__init__.py
creme/facto/fwfm.py
creme/compose/pipeline.py
creme/compose/rename.py
creme/compose/select.py
creme/compose/union.py
creme/compose/func.py
creme/compose/__init__.py
creme/compose/test_.py
creme/compose/grouper.py
creme/stats/ewmean.py
creme/stats/maximum.py
creme/stats/link.py
creme/stats/base.cpython-37m-x86_64-linux-gnu.so
creme/stats/pearson.py
creme/stats/ptp.py
creme/stats/quantile.py
creme/stats/var.c
creme/stats/sem.py
creme/stats/base.pxd
creme/stats/cov.py
creme/stats/moments.py
creme/stats/mean.pyx
creme/stats/summing.py
creme/stats/base.c
creme/stats/minimum.py
creme/stats/var.cpython-37m-x86_64-linux-gnu.so
creme/stats/count.py
creme/stats/skew.py
creme/stats/ewvar.py
creme/stats/iqr.py
creme/stats/mean.c
creme/stats/mode.py
creme/stats/base.pyx
creme/stats/__init__.py
creme/stats/mean.pxd
creme/stats/var.pyx
