Metadata-Version: 2.1
Name: creme
Version: 0.6.1
Summary: Online machine learning in Python
Home-page: https://github.com/creme-ml/creme
Author: Max Halford
Author-email: maxhalford25@gmail.com
License: BSD-3
Platform: UNKNOWN
Classifier: License :: OSI Approved :: BSD License
Classifier: Programming Language :: Python
Classifier: Programming Language :: Python :: 3
Classifier: Programming Language :: Python :: 3.6
Classifier: Programming Language :: Python :: 3.7
Classifier: Programming Language :: Python :: 3.8
Classifier: Programming Language :: Python :: Implementation :: CPython
Classifier: Programming Language :: Python :: Implementation :: PyPy
Requires-Python: >=3.6.0
Provides-Extra: docs
Provides-Extra: compat
Provides-Extra: dev
